<annotation>
	<folder>my-project-name</folder>
	<filename>Tree_133.jpg</filename>
	<path>/my-project-name/Tree_133.jpg</path>
	<source>
		<database>Unspecified</database>
	</source>
	<size>
		<width>1111</width>
		<height>1111</height>
		<depth>3</depth>
	</size>
	<object>
		<name>Tree</name>
		<pose>Unspecified</pose>
		<truncated>0</truncated>
		<difficult>0</difficult>
		<bndbox>
			<xmin>109</xmin>
			<ymin>96</ymin>
			<xmax>1025</xmax>
			<ymax>1000</ymax>
		</bndbox>
	</object>
</annotation>